{"py/object": "rasa.core.featurizers.tracker_featurizers.MaxHistoryTrackerFeaturizer", "state_featurizer": {"py/object": "rasa.core.featurizers.single_state_featurizer.SingleStateFeaturizer", "_default_feature_states": {"intent": {"EXTERNAL_page_change": 0, "ancient_appearance": 1, "ancient_location": 2, "architecture_info": 3, "back": 4, "bot_challenge": 5, "conocchia_enclosure": 6, "current_state": 7, "dimension": 8, "domus_confuleius_floors": 9, "domus_confuleius_inscriptions": 10, "domus_confuleius_inscriptions_location": 11, "domus_confuleius_owner": 12, "domus_confuleius_rooms": 13, "domus_rooms": 14, "domus_via_orti_cubiculum_floor": 15, "domus_via_orti_entrance": 16, "domus_via_orti_spa": 17, "domus_via_orti_thermal_rooms": 18, "domus_via_orti_triclinium_floor": 19, "goodbye": 20, "greet": 21, "info_path": 22, "monument_date": 23, "monument_depictions": 24, "monument_discovered": 25, "monument_epigraph": 26, "monument_function": 27, "monument_material": 28, "monument_restoration": 29, "my_location": 30, "name_meaning": 31, "nlu_fallback": 32, "out_of_scope": 33, "restart": 34, "session_start": 35, "what_is": 36, "where_is": 37, "who_is": 38}, "action_name": {"action_listen": 0, "action_restart": 1, "action_session_start": 2, "action_default_fallback": 3, "action_deactivate_loop": 4, "action_revert_fallback_events": 5, "action_default_ask_affirmation": 6, "action_default_ask_rephrase": 7, "action_two_stage_fallback": 8, "action_unlikely_intent": 9, "action_back": 10, "...": 11, "action_extract_slots": 12, "action_set_Topic": 13, "send_Topic": 14, "utter_EXTERNAL_page_change": 15, "utter_ancient_appearance": 16, "utter_ancient_location": 17, "utter_architecture_info": 18, "utter_ask_topic": 19, "utter_bot_challenge": 20, "utter_conocchia_enclosure": 21, "utter_current_state": 22, "utter_dimension": 23, "utter_domus_confuleius_floors": 24, "utter_domus_confuleius_inscriptions": 25, "utter_domus_confuleius_inscriptions_location": 26, "utter_domus_confuleius_owner": 27, "utter_domus_confuleius_rooms": 28, "utter_domus_rooms": 29, "utter_domus_via_orti_cubiculum_floor": 30, "utter_domus_via_orti_entrance": 31, "utter_domus_via_orti_spa": 32, "utter_domus_via_orti_thermal_rooms": 33, "utter_domus_via_orti_triclinium_floor": 34, "utter_goodbye": 35, "utter_greet": 36, "utter_info_path": 37, "utter_monument_date": 38, "utter_monument_depictions": 39, "utter_monument_discovered": 40, "utter_monument_epigraph": 41, "utter_monument_function": 42, "utter_monument_material": 43, "utter_monument_restoration": 44, "utter_my_location": 45, "utter_name_meaning": 46, "utter_what_is": 47, "utter_where_is": 48, "utter_who_is": 49}, "entities": {"annotation_url": 0, "page_url": 1, "pan_x": 2, "pan_y": 3, "topic": 4, "word": 5, "zoom_factor": 6, "zoom_x": 7, "zoom_y": 8}, "slots": {"topic_0": 0, "topic_1": 1, "topic_2": 2, "topic_3": 3, "topic_4": 4, "topic_5": 5, "topic_6": 6, "topic_7": 7, "topic_8": 8, "topic_9": 9, "topic_10": 10, "topic_11": 11, "topic_12": 12, "topic_13": 13, "word_0": 14, "word_1": 15, "word_2": 16, "word_3": 17, "word_4": 18, "word_5": 19, "word_6": 20, "word_7": 21}, "active_loop": {}}, "action_texts": [], "entity_tag_specs": null}, "max_history": 10, "remove_duplicates": true}